Metadata-Version: 2.4
Name: bandwitch
Version: 0.3.7
Summary: Enzyme selection for DNA verification and identification.
Author: Zulko
License-Expression: MIT
Project-URL: Homepage, https://github.com/Edinburgh-Genome-Foundry/bandwitch
Keywords: restriction,enzyme,synthetic biology,DNA,band,pattern
License-File: LICENSE
Requires-Dist: tqdm
Requires-Dist: biopython
Requires-Dist: scipy
Requires-Dist: matplotlib
Requires-Dist: bandwagon
Requires-Dist: dna_features_viewer
Requires-Dist: flametree
Requires-Dist: pandas
Dynamic: license-file
